sae_bench/__init__.py
sae_bench/custom_saes/README.md
sae_bench/custom_saes/base_sae.py
sae_bench/custom_saes/batch_topk_sae.py
sae_bench/custom_saes/custom_sae_config.py
sae_bench/custom_saes/gated_sae.py
sae_bench/custom_saes/identity_sae.py
sae_bench/custom_saes/jumprelu_sae.py
sae_bench/custom_saes/pca_sae.py
sae_bench/custom_saes/relu_sae.py
sae_bench/custom_saes/run_all_evals_custom_saes.py
sae_bench/custom_saes/run_all_evals_dictionary_learning_saes.py
sae_bench/custom_saes/topk_sae.py
sae_bench/evals/absorption/README.md
sae_bench/evals/absorption/__init__.py
sae_bench/evals/absorption/common.py
sae_bench/evals/absorption/eval_config.py
sae_bench/evals/absorption/eval_output.py
sae_bench/evals/absorption/eval_output_schema_absorption_first_letter.json
sae_bench/evals/absorption/feature_absorption.py
sae_bench/evals/absorption/feature_absorption_calculator.py
sae_bench/evals/absorption/k_sparse_probing.py
sae_bench/evals/absorption/main.py
sae_bench/evals/absorption/probing.py
sae_bench/evals/absorption/prompting.py
sae_bench/evals/absorption/util.py
sae_bench/evals/absorption/vocab.py
sae_bench/evals/autointerp/README.md
sae_bench/evals/autointerp/demo.py
sae_bench/evals/autointerp/eval_config.py
sae_bench/evals/autointerp/eval_output.py
sae_bench/evals/autointerp/eval_output_schema_autointerp.json
sae_bench/evals/autointerp/logs_100.txt
sae_bench/evals/autointerp/logs_4.txt
sae_bench/evals/autointerp/main.py
sae_bench/evals/autointerp/mlp_neurons_vs_saes.py
sae_bench/evals/autointerp/sae_encode.py
sae_bench/evals/base_eval_output.py
sae_bench/evals/core/convert_directory.py
sae_bench/evals/core/eval_config.py
sae_bench/evals/core/eval_output.py
sae_bench/evals/core/eval_output_schema_core.json
sae_bench/evals/core/main.py
sae_bench/evals/generate_json_schemas.py
sae_bench/evals/mdl/README.md
sae_bench/evals/mdl/eval_config.py
sae_bench/evals/mdl/graphing_mdl.ipynb
sae_bench/evals/mdl/main.py
sae_bench/evals/meta_structure/README.md
sae_bench-0.5.1.dist-info/METADATA
sae_bench-0.5.1.dist-info/WHEEL
sae_bench-0.5.1.dist-info/RECORD
