Metadata-Version: 2.4
Name: sae-bench
Version: 0.5.1
Summary: A framework for evaluating sparse autoencoders
Keywords: sparse-autoencoders,mechanistic-interpretability,PyTorch
Author: Adam Karvonen
Author-email: adam.karvonen@gmail.com
Requires-Python: >=3.10,<4.0
Classifier: Programming Language :: Python :: 3
Classifier: Programming Language :: Python :: 3.10
Classifier: Programming Language :: Python :: 3.11
Classifier: Programming Language :: Python :: 3.12
Classifier: Programming Language :: Python :: 3.13
Classifier: Programming Language :: Python :: 3.14
Classifier: Topic :: Scientific/Engineering :: Artificial Intelligence
Requires-Dist: beartype (>=0.14.1)
Requires-Dist: collectibles (>=0.1.5)
Requires-Dist: datasets (>=3.0.0,<4.0.0)
Requires-Dist: einops (>=0.8.0)
Requires-Dist: jaxtyping (>=0.2.25)
Requires-Dist: matplotlib (>=3.8.4)
Requires-Dist: numpy (>=1.26.4,<2.0)
Requires-Dist: openai (>=1.0.0)
Requires-Dist: pandas (>=2.1.2)
Requires-Dist: plotly (>=5.22.0)
Requires-Dist: pydantic (>=2.9.2)
Requires-Dist: sae-probes (>=0.3.0,<0.4.0)
Requires-Dist: sae_lens (>=6.22.2,<7.0.0)
Requires-Dist: scikit-learn (>=1.5.2)
Requires-Dist: seaborn (>=0.13.2)
Requires-Dist: tabulate (>=0.9.0)
Requires-Dist: torch (>=2.1.0)
Requires-Dist: torchvision (>=0.16.1)
Requires-Dist: tqdm (>=4.66.4)
Requires-Dist: transformer-lens (>=2.0.0)
Project-URL: Repository, https://github.com/adamkarvonen/SAEBench
